LICENSE
MANIFEST.in
README.rst
dev-requirements.txt
setup.cfg
setup.py
tasks-requirements.txt
tasks.py
local_convocations/__init__.py
local_convocations/_version.py
local_convocations/autodoc.py
local_convocations/checks.py
local_convocations/console.py
local_convocations/docs.py
local_convocations/pytest.py
local_convocations/testing.py
local_convocations/travis.py
local_convocations/util.py
local_convocations/watch.py
local_convocations/packaging/__init__.py
local_convocations/packaging/release.py
local_convocations/packaging/semantic_version_monkey.py
local_convocations/packaging/vendorize.py
raft/__init__.py
raft/__main__.py
raft/_version.py
raft/collection.py
raft/config.py
raft/context.py
raft/env.py
raft/exceptions.py
raft/executor.py
raft/loader.py
raft/main.py
raft/program.py
raft/runners.py
raft/tasks.py
raft/terminals.py
raft/util.py
raft/watchers.py
raft.egg-info/PKG-INFO
raft.egg-info/SOURCES.txt
raft.egg-info/dependency_links.txt
raft.egg-info/entry_points.txt
raft.egg-info/top_level.txt
raft/completion/__init__.py
raft/completion/bash.completion
raft/completion/complete.py
raft/completion/fish.completion
raft/completion/zsh.completion
raft/parser/__init__.py
raft/parser/argument.py
raft/parser/context.py
raft/parser/parser.py
raft/vendor/__init__.py
raft/vendor/decorator.py
raft/vendor/six.py
raft/vendor/fluidity/__init__.py
raft/vendor/fluidity/backwardscompat.py
raft/vendor/fluidity/machine.py
raft/vendor/lexicon/__init__.py
raft/vendor/lexicon/alias_dict.py
raft/vendor/lexicon/attribute_dict.py
raft/vendor/yaml3/__init__.py
raft/vendor/yaml3/composer.py
raft/vendor/yaml3/constructor.py
raft/vendor/yaml3/cyaml.py
raft/vendor/yaml3/dumper.py
raft/vendor/yaml3/emitter.py
raft/vendor/yaml3/error.py
raft/vendor/yaml3/events.py
raft/vendor/yaml3/loader.py
raft/vendor/yaml3/nodes.py
raft/vendor/yaml3/parser.py
raft/vendor/yaml3/reader.py
raft/vendor/yaml3/representer.py
raft/vendor/yaml3/resolver.py
raft/vendor/yaml3/scanner.py
raft/vendor/yaml3/serializer.py
raft/vendor/yaml3/tokens.py
sites/shared_conf.py
sites/docs/conf.py
sites/docs/getting-started.rst
sites/docs/index.rst
